flask_bucket.py
flask_bucket-0.0.1.dist-info/LICENSE
flask_bucket-0.0.1.dist-info/METADATA
flask_bucket-0.0.1.dist-info/WHEEL
flask_bucket-0.0.1.dist-info/top_level.txt
flask_bucket-0.0.1.dist-info/RECORD
