Metadata-Version: 2.1
Name: flask-bucket
Version: 0.0.1
Summary: Create flask modules using a flask shell command
Home-page: https://github.com/owen-eternal/flask-bucket
Author: Owen O. Phakade
Author-email: olwethuphakade89@gmail.com
License: BSD
Platform: any
Classifier: Environment :: Web Environment
Classifier: Intended Audience :: Developers
Classifier: License :: OSI Approved :: BSD License
Classifier: Operating System :: OS Independent
Classifier: Programming Language :: Python
Classifier: Topic :: Internet :: WWW/HTTP :: Dynamic Content
Classifier: Topic :: Software Development :: Libraries :: Python Modules
Requires-Dist: Flask
Provides-Extra: dev
Requires-Dist: pytest (>=3.7) ; extra == 'dev'
